Metadata-Version: 1.0
Name: X11Client
Version: 1.4
Summary: X11 client
Home-page: http://github.com/diegorubin/X11Client
Author: Diego Rubin
Author-email: rubin.diego@gmail.com
License: UNKNOWN
Platform: UNKNOWN
